{
  "algo_id": "baseline_partition_lawnmower_v2",
  "status": "FAILED",
  "scene_id": "scene_05_narrow_corridor",
  "coverage_ratio": 0.8753623188405797,
  "path_length_m": 1643.8962645237957,
  "estimated_time_sec": 547.9654215079319,
  "path_points": 1603,
  "total_cells": 690,
  "covered_cells": 604,
  "vehicle_name": "Drone1",
  "config": {
    "cell_size": 2.0,
    "speed": 3.0,
    "altitude": -100.0
  },
  "path": [
    [
      2.0,
      1.0,
      -100.0
    ],
    [
      4.0,
      1.0,
      -100.0
    ],
    [
      6.0,
      1.0,
      -100.0
    ],
    [
      8.0,
      1.0,
      -100.0
    ],
    [
      10.0,
      1.0,
      -100.0
    ],
    [
      12.0,
      1.0,
      -100.0
    ],
    [
      14.0,
      1.0,
      -100.0
    ],
    [
      16.0,
      1.0,
      -100.0
    ],
    [
      18.0,
      1.0,
      -100.0
    ],
    [
      20.0,
      1.0,
      -100.0
    ],
    [
      22.0,
      1.0,
      -100.0
    ],
    [
      24.0,
      1.0,
      -100.0
    ],
    [
      26.0,
      1.0,
      -100.0
    ],
    [
      28.0,
      1.0,
      -100.0
    ],
    [
      30.0,
      1.0,
      -100.0
    ],
    [
      32.0,
      1.0,
      -100.0
    ],
    [
      34.0,
      1.0,
      -100.0
    ],
    [
      36.0,
      1.0,
      -100.0
    ],
    [
      38.0,
      1.0,
      -100.0
    ],
    [
      40.0,
      1.0,
      -100.0
    ],
    [
      42.0,
      1.0,
      -100.0
    ],
    [
      44.0,
      1.0,
      -100.0
    ],
    [
      46.0,
      1.0,
      -100.0
    ],
    [
      48.0,
      1.0,
      -100.0
    ],
    [
      50.0,
      1.0,
      -100.0
    ],
    [
      52.0,
      1.0,
      -100.0
    ],
    [
      54.0,
      1.0,
      -100.0
    ],
    [
      56.0,
      1.0,
      -100.0
    ],
    [
      58.0,
      1.0,
      -100.0
    ],
    [
      60.0,
      1.0,
      -100.0
    ],
    [
      62.0,
      1.0,
      -100.0
    ],
    [
      64.0,
      1.0,
      -100.0
    ],
    [
      66.0,
      1.0,
      -100.0
    ],
    [
      68.0,
      1.0,
      -100.0
    ],
    [
      70.0,
      1.0,
      -100.0
    ],
    [
      72.0,
      1.0,
      -100.0
    ],
    [
      74.0,
      1.0,
      -100.0
    ],
    [
      76.0,
      1.0,
      -100.0
    ],
    [
      78.0,
      1.0,
      -100.0
    ],
    [
      80.0,
      1.0,
      -100.0
    ],
    [
      82.0,
      1.0,
      -100.0
    ],
    [
      84.0,
      1.0,
      -100.0
    ],
    [
      86.0,
      1.0,
      -100.0
    ],
    [
      88.0,
      1.0,
      -100.0
    ],
    [
      90.0,
      1.0,
      -100.0
    ],
    [
      92.0,
      1.0,
      -100.0
    ],
    [
      94.0,
      1.0,
      -100.0
    ],
    [
      96.0,
      1.0,
      -100.0
    ],
    [
      98.0,
      1.0,
      -100.0
    ],
    [
      100.0,
      1.0,
      -100.0
    ],
    [
      102.0,
      1.0,
      -100.0
    ],
    [
      104.0,
      1.0,
      -100.0
    ],
    [
      106.0,
      1.0,
      -100.0
    ],
    [
      108.0,
      1.0,
      -100.0
    ],
    [
      110.0,
      1.0,
      -100.0
    ],
    [
      112.0,
      1.0,
      -100.0
    ],
    [
      114.0,
      1.0,
      -100.0
    ],
    [
      116.0,
      1.0,
      -100.0
    ],
    [
      118.0,
      1.0,
      -100.0
    ],
    [
      120.0,
      1.0,
      -100.0
    ],
    [
      122.0,
      1.0,
      -100.0
    ],
    [
      124.0,
      1.0,
      -100.0
    ],
    [
      126.0,
      1.0,
      -100.0
    ],
    [
      128.0,
      1.0,
      -100.0
    ],
    [
      130.0,
      1.0,
      -100.0
    ],
    [
      132.0,
      1.0,
      -100.0
    ],
    [
      134.0,
      1.0,
      -100.0
    ],
    [
      136.0,
      3.0,
      -100.0
    ],
    [
      134.0,
      3.0,
      -100.0
    ],
    [
      132.0,
      3.0,
      -100.0
    ],
    [
      130.0,
      3.0,
      -100.0
    ],
    [
      128.0,
      3.0,
      -100.0
    ],
    [
      126.0,
      3.0,
      -100.0
    ],
    [
      124.0,
      3.0,
      -100.0
    ],
    [
      122.0,
      3.0,
      -100.0
    ],
    [
      120.0,
      3.0,
      -100.0
    ],
    [
      118.0,
      3.0,
      -100.0
    ],
    [
      116.0,
      3.0,
      -100.0
    ],
    [
      114.0,
      3.0,
      -100.0
    ],
    [
      112.0,
      3.0,
      -100.0
    ],
    [
      110.0,
      3.0,
      -100.0
    ],
    [
      108.0,
      3.0,
      -100.0
    ],
    [
      106.0,
      3.0,
      -100.0
    ],
    [
      104.0,
      3.0,
      -100.0
    ],
    [
      102.0,
      3.0,
      -100.0
    ],
    [
      100.0,
      3.0,
      -100.0
    ],
    [
      98.0,
      3.0,
      -100.0
    ],
    [
      96.0,
      3.0,
      -100.0
    ],
    [
      94.0,
      3.0,
      -100.0
    ],
    [
      92.0,
      3.0,
      -100.0
    ],
    [
      90.0,
      3.0,
      -100.0
    ],
    [
      88.0,
      3.0,
      -100.0
    ],
    [
      86.0,
      3.0,
      -100.0
    ],
    [
      84.0,
      3.0,
      -100.0
    ],
    [
      82.0,
      3.0,
      -100.0
    ],
    [
      80.0,
      3.0,
      -100.0
    ],
    [
      78.0,
      3.0,
      -100.0
    ],
    [
      76.0,
      3.0,
      -100.0
    ],
    [
      74.0,
      3.0,
      -100.0
    ],
    [
      72.0,
      3.0,
      -100.0
    ],
    [
      70.0,
      3.0,
      -100.0
    ],
    [
      68.0,
      3.0,
      -100.0
    ],
    [
      66.0,
      3.0,
      -100.0
    ],
    [
      64.0,
      3.0,
      -100.0
    ],
    [
      62.0,
      3.0,
      -100.0
    ],
    [
      60.0,
      3.0,
      -100.0
    ],
    [
      58.0,
      3.0,
      -100.0
    ],
    [
      56.0,
      3.0,
      -100.0
    ],
    [
      54.0,
      3.0,
      -100.0
    ],
    [
      52.0,
      3.0,
      -100.0
    ],
    [
      50.0,
      3.0,
      -100.0
    ],
    [
      48.0,
      3.0,
      -100.0
    ],
    [
      46.0,
      3.0,
      -100.0
    ],
    [
      44.0,
      3.0,
      -100.0
    ],
    [
      42.0,
      3.0,
      -100.0
    ],
    [
      40.0,
      3.0,
      -100.0
    ],
    [
      38.0,
      3.0,
      -100.0
    ],
    [
      36.0,
      3.0,
      -100.0
    ],
    [
      34.0,
      3.0,
      -100.0
    ],
    [
      32.0,
      3.0,
      -100.0
    ],
    [
      30.0,
      3.0,
      -100.0
    ],
    [
      28.0,
      3.0,
      -100.0
    ],
    [
      26.0,
      3.0,
      -100.0
    ],
    [
      24.0,
      3.0,
      -100.0
    ],
    [
      22.0,
      3.0,
      -100.0
    ],
    [
      20.0,
      3.0,
      -100.0
    ],
    [
      18.0,
      3.0,
      -100.0
    ],
    [
      16.0,
      3.0,
      -100.0
    ],
    [
      14.0,
      3.0,
      -100.0
    ],
    [
      12.0,
      3.0,
      -100.0
    ],
    [
      10.0,
      3.0,
      -100.0
    ],
    [
      8.0,
      3.0,
      -100.0
    ],
    [
      6.0,
      3.0,
      -100.0
    ],
    [
      4.0,
      3.0,
      -100.0
    ],
    [
      2.0,
      5.0,
      -100.0
    ],
    [
      4.0,
      5.0,
      -100.0
    ],
    [
      6.0,
      5.0,
      -100.0
    ],
    [
      8.0,
      5.0,
      -100.0
    ],
    [
      10.0,
      5.0,
      -100.0
    ],
    [
      12.0,
      5.0,
      -100.0
    ],
    [
      14.0,
      5.0,
      -100.0
    ],
    [
      16.0,
      5.0,
      -100.0
    ],
    [
      18.0,
      5.0,
      -100.0
    ],
    [
      20.0,
      5.0,
      -100.0
    ],
    [
      22.0,
      5.0,
      -100.0
    ],
    [
      24.0,
      5.0,
      -100.0
    ],
    [
      26.0,
      5.0,
      -100.0
    ],
    [
      28.0,
      5.0,
      -100.0
    ],
    [
      30.0,
      5.0,
      -100.0
    ],
    [
      32.0,
      5.0,
      -100.0
    ],
    [
      34.0,
      5.0,
      -100.0
    ],
    [
      36.0,
      5.0,
      -100.0
    ],
    [
      38.0,
      5.0,
      -100.0
    ],
    [
      40.0,
      5.0,
      -100.0
    ],
    [
      42.0,
      5.0,
      -100.0
    ],
    [
      44.0,
      5.0,
      -100.0
    ],
    [
      46.0,
      5.0,
      -100.0
    ],
    [
      48.0,
      5.0,
      -100.0
    ],
    [
      50.0,
      5.0,
      -100.0
    ],
    [
      52.0,
      5.0,
      -100.0
    ],
    [
      54.0,
      5.0,
      -100.0
    ],
    [
      56.0,
      5.0,
      -100.0
    ],
    [
      58.0,
      5.0,
      -100.0
    ],
    [
      60.0,
      5.0,
      -100.0
    ],
    [
      62.0,
      5.0,
      -100.0
    ],
    [
      64.0,
      5.0,
      -100.0
    ],
    [
      66.0,
      5.0,
      -100.0
    ],
    [
      68.0,
      5.0,
      -100.0
    ],
    [
      70.0,
      5.0,
      -100.0
    ],
    [
      72.0,
      5.0,
      -100.0
    ],
    [
      74.0,
      5.0,
      -100.0
    ],
    [
      76.0,
      5.0,
      -100.0
    ],
    [
      78.0,
      5.0,
      -100.0
    ],
    [
      80.0,
      5.0,
      -100.0
    ],
    [
      82.0,
      5.0,
      -100.0
    ],
    [
      84.0,
      5.0,
      -100.0
    ],
    [
      86.0,
      5.0,
      -100.0
    ],
    [
      88.0,
      5.0,
      -100.0
    ],
    [
      90.0,
      5.0,
      -100.0
    ],
    [
      92.0,
      5.0,
      -100.0
    ],
    [
      94.0,
      5.0,
      -100.0
    ],
    [
      96.0,
      5.0,
      -100.0
    ],
    [
      98.0,
      5.0,
      -100.0
    ],
    [
      100.0,
      5.0,
      -100.0
    ],
    [
      102.0,
      5.0,
      -100.0
    ],
    [
      104.0,
      5.0,
      -100.0
    ],
    [
      106.0,
      5.0,
      -100.0
    ],
    [
      108.0,
      5.0,
      -100.0
    ],
    [
      110.0,
      5.0,
      -100.0
    ],
    [
      112.0,
      5.0,
      -100.0
    ],
    [
      114.0,
      5.0,
      -100.0
    ],
    [
      116.0,
      5.0,
      -100.0
    ],
    [
      118.0,
      5.0,
      -100.0
    ],
    [
      120.0,
      5.0,
      -100.0
    ],
    [
      122.0,
      5.0,
      -100.0
    ],
    [
      124.0,
      5.0,
      -100.0
    ],
    [
      126.0,
      5.0,
      -100.0
    ],
    [
      128.0,
      5.0,
      -100.0
    ],
    [
      130.0,
      5.0,
      -100.0
    ],
    [
      132.0,
      5.0,
      -100.0
    ],
    [
      134.0,
      5.0,
      -100.0
    ],
    [
      136.0,
      7.0,
      -100.0
    ],
    [
      134.0,
      7.0,
      -100.0
    ],
    [
      132.0,
      7.0,
      -100.0
    ],
    [
      130.0,
      7.0,
      -100.0
    ],
    [
      128.0,
      7.0,
      -100.0
    ],
    [
      126.0,
      7.0,
      -100.0
    ],
    [
      124.0,
      7.0,
      -100.0
    ],
    [
      122.0,
      7.0,
      -100.0
    ],
    [
      120.0,
      7.0,
      -100.0
    ],
    [
      118.0,
      7.0,
      -100.0
    ],
    [
      116.0,
      7.0,
      -100.0
    ],
    [
      114.0,
      7.0,
      -100.0
    ],
    [
      112.0,
      7.0,
      -100.0
    ],
    [
      110.0,
      7.0,
      -100.0
    ],
    [
      108.0,
      7.0,
      -100.0
    ],
    [
      106.0,
      7.0,
      -100.0
    ],
    [
      104.0,
      7.0,
      -100.0
    ],
    [
      102.0,
      7.0,
      -100.0
    ],
    [
      100.0,
      7.0,
      -100.0
    ],
    [
      98.0,
      7.0,
      -100.0
    ],
    [
      96.0,
      7.0,
      -100.0
    ],
    [
      94.0,
      7.0,
      -100.0
    ],
    [
      92.0,
      7.0,
      -100.0
    ],
    [
      90.0,
      7.0,
      -100.0
    ],
    [
      88.0,
      7.0,
      -100.0
    ],
    [
      86.0,
      7.0,
      -100.0
    ],
    [
      84.0,
      7.0,
      -100.0
    ],
    [
      82.0,
      7.0,
      -100.0
    ],
    [
      80.0,
      7.0,
      -100.0
    ],
    [
      78.0,
      7.0,
      -100.0
    ],
    [
      76.0,
      7.0,
      -100.0
    ],
    [
      74.0,
      7.0,
      -100.0
    ],
    [
      72.0,
      7.0,
      -100.0
    ],
    [
      70.0,
      7.0,
      -100.0
    ],
    [
      68.0,
      7.0,
      -100.0
    ],
    [
      66.0,
      7.0,
      -100.0
    ],
    [
      64.0,
      7.0,
      -100.0
    ],
    [
      62.0,
      7.0,
      -100.0
    ],
    [
      60.0,
      7.0,
      -100.0
    ],
    [
      58.0,
      7.0,
      -100.0
    ],
    [
      56.0,
      7.0,
      -100.0
    ],
    [
      54.0,
      7.0,
      -100.0
    ],
    [
      52.0,
      7.0,
      -100.0
    ],
    [
      50.0,
      7.0,
      -100.0
    ],
    [
      48.0,
      7.0,
      -100.0
    ],
    [
      46.0,
      7.0,
      -100.0
    ],
    [
      44.0,
      7.0,
      -100.0
    ],
    [
      42.0,
      7.0,
      -100.0
    ],
    [
      40.0,
      7.0,
      -100.0
    ],
    [
      38.0,
      7.0,
      -100.0
    ],
    [
      36.0,
      7.0,
      -100.0
    ],
    [
      34.0,
      7.0,
      -100.0
    ],
    [
      32.0,
      7.0,
      -100.0
    ],
    [
      30.0,
      7.0,
      -100.0
    ],
    [
      28.0,
      7.0,
      -100.0
    ],
    [
      26.0,
      7.0,
      -100.0
    ],
    [
      24.0,
      7.0,
      -100.0
    ],
    [
      22.0,
      7.0,
      -100.0
    ],
    [
      20.0,
      7.0,
      -100.0
    ],
    [
      18.0,
      7.0,
      -100.0
    ],
    [
      16.0,
      7.0,
      -100.0
    ],
    [
      14.0,
      7.0,
      -100.0
    ],
    [
      12.0,
      7.0,
      -100.0
    ],
    [
      10.0,
      7.0,
      -100.0
    ],
    [
      8.0,
      7.0,
      -100.0
    ],
    [
      6.0,
      7.0,
      -100.0
    ],
    [
      4.0,
      7.0,
      -100.0
    ],
    [
      2.0,
      9.0,
      -100.0
    ],
    [
      4.0,
      9.0,
      -100.0
    ],
    [
      6.0,
      9.0,
      -100.0
    ],
    [
      8.0,
      9.0,
      -100.0
    ],
    [
      10.0,
      9.0,
      -100.0
    ],
    [
      12.0,
      9.0,
      -100.0
    ],
    [
      14.0,
      9.0,
      -100.0
    ],
    [
      16.0,
      9.0,
      -100.0
    ],
    [
      18.0,
      9.0,
      -100.0
    ],
    [
      20.0,
      9.0,
      -100.0
    ],
    [
      22.0,
      9.0,
      -100.0
    ],
    [
      24.0,
      9.0,
      -100.0
    ],
    [
      26.0,
      9.0,
      -100.0
    ],
    [
      28.0,
      9.0,
      -100.0
    ],
    [
      30.0,
      9.0,
      -100.0
    ],
    [
      32.0,
      9.0,
      -100.0
    ],
    [
      34.0,
      9.0,
      -100.0
    ],
    [
      36.0,
      9.0,
      -100.0
    ],
    [
      38.0,
      9.0,
      -100.0
    ],
    [
      40.0,
      9.0,
      -100.0
    ],
    [
      42.0,
      9.0,
      -100.0
    ],
    [
      44.0,
      9.0,
      -100.0
    ],
    [
      46.0,
      9.0,
      -100.0
    ],
    [
      48.0,
      9.0,
      -100.0
    ],
    [
      50.0,
      9.0,
      -100.0
    ],
    [
      52.0,
      9.0,
      -100.0
    ],
    [
      54.0,
      9.0,
      -100.0
    ],
    [
      56.0,
      9.0,
      -100.0
    ],
    [
      58.0,
      9.0,
      -100.0
    ],
    [
      60.0,
      9.0,
      -100.0
    ],
    [
      62.0,
      9.0,
      -100.0
    ],
    [
      64.0,
      9.0,
      -100.0
    ],
    [
      66.0,
      9.0,
      -100.0
    ],
    [
      68.0,
      9.0,
      -100.0
    ],
    [
      70.0,
      9.0,
      -100.0
    ],
    [
      72.0,
      9.0,
      -100.0
    ],
    [
      74.0,
      9.0,
      -100.0
    ],
    [
      76.0,
      9.0,
      -100.0
    ],
    [
      78.0,
      9.0,
      -100.0
    ],
    [
      80.0,
      9.0,
      -100.0
    ],
    [
      82.0,
      9.0,
      -100.0
    ],
    [
      84.0,
      9.0,
      -100.0
    ],
    [
      86.0,
      9.0,
      -100.0
    ],
    [
      88.0,
      9.0,
      -100.0
    ],
    [
      90.0,
      9.0,
      -100.0
    ],
    [
      92.0,
      9.0,
      -100.0
    ],
    [
      94.0,
      9.0,
      -100.0
    ],
    [
      96.0,
      9.0,
      -100.0
    ],
    [
      98.0,
      9.0,
      -100.0
    ],
    [
      100.0,
      9.0,
      -100.0
    ],
    [
      102.0,
      9.0,
      -100.0
    ],
    [
      104.0,
      9.0,
      -100.0
    ],
    [
      106.0,
      9.0,
      -100.0
    ],
    [
      108.0,
      9.0,
      -100.0
    ],
    [
      110.0,
      9.0,
      -100.0
    ],
    [
      112.0,
      9.0,
      -100.0
    ],
    [
      114.0,
      9.0,
      -100.0
    ],
    [
      116.0,
      9.0,
      -100.0
    ],
    [
      118.0,
      9.0,
      -100.0
    ],
    [
      120.0,
      9.0,
      -100.0
    ],
    [
      122.0,
      9.0,
      -100.0
    ],
    [
      124.0,
      9.0,
      -100.0
    ],
    [
      126.0,
      9.0,
      -100.0
    ],
    [
      128.0,
      9.0,
      -100.0
    ],
    [
      130.0,
      9.0,
      -100.0
    ],
    [
      132.0,
      9.0,
      -100.0
    ],
    [
      134.0,
      9.0,
      -100.0
    ],
    [
      136.0,
      11.0,
      -100.0
    ],
    [
      134.0,
      11.0,
      -100.0
    ],
    [
      132.0,
      11.0,
      -100.0
    ],
    [
      130.0,
      11.0,
      -100.0
    ],
    [
      128.0,
      11.0,
      -100.0
    ],
    [
      126.0,
      11.0,
      -100.0
    ],
    [
      124.0,
      11.0,
      -100.0
    ],
    [
      122.0,
      11.0,
      -100.0
    ],
    [
      120.0,
      11.0,
      -100.0
    ],
    [
      118.0,
      11.0,
      -100.0
    ],
    [
      116.0,
      11.0,
      -100.0
    ],
    [
      114.0,
      11.0,
      -100.0
    ],
    [
      112.0,
      11.0,
      -100.0
    ],
    [
      110.0,
      11.0,
      -100.0
    ],
    [
      108.0,
      11.0,
      -100.0
    ],
    [
      106.0,
      11.0,
      -100.0
    ],
    [
      104.0,
      11.0,
      -100.0
    ],
    [
      102.0,
      11.0,
      -100.0
    ],
    [
      100.0,
      11.0,
      -100.0
    ],
    [
      98.0,
      11.0,
      -100.0
    ],
    [
      96.0,
      11.0,
      -100.0
    ],
    [
      94.0,
      11.0,
      -100.0
    ],
    [
      92.0,
      11.0,
      -100.0
    ],
    [
      90.0,
      11.0,
      -100.0
    ],
    [
      88.0,
      11.0,
      -100.0
    ],
    [
      86.0,
      11.0,
      -100.0
    ],
    [
      84.0,
      11.0,
      -100.0
    ],
    [
      82.0,
      11.0,
      -100.0
    ],
    [
      80.0,
      11.0,
      -100.0
    ],
    [
      78.0,
      11.0,
      -100.0
    ],
    [
      76.0,
      11.0,
      -100.0
    ],
    [
      74.0,
      11.0,
      -100.0
    ],
    [
      72.0,
      11.0,
      -100.0
    ],
    [
      70.0,
      11.0,
      -100.0
    ],
    [
      68.0,
      11.0,
      -100.0
    ],
    [
      66.0,
      11.0,
      -100.0
    ],
    [
      64.0,
      11.0,
      -100.0
    ],
    [
      62.0,
      11.0,
      -100.0
    ],
    [
      60.0,
      11.0,
      -100.0
    ],
    [
      58.0,
      11.0,
      -100.0
    ],
    [
      56.0,
      11.0,
      -100.0
    ],
    [
      54.0,
      11.0,
      -100.0
    ],
    [
      52.0,
      11.0,
      -100.0
    ],
    [
      50.0,
      11.0,
      -100.0
    ],
    [
      48.0,
      11.0,
      -100.0
    ],
    [
      46.0,
      11.0,
      -100.0
    ],
    [
      44.0,
      11.0,
      -100.0
    ],
    [
      42.0,
      11.0,
      -100.0
    ],
    [
      40.0,
      11.0,
      -100.0
    ],
    [
      38.0,
      11.0,
      -100.0
    ],
    [
      36.0,
      11.0,
      -100.0
    ],
    [
      34.0,
      11.0,
      -100.0
    ],
    [
      32.0,
      11.0,
      -100.0
    ],
    [
      30.0,
      11.0,
      -100.0
    ],
    [
      28.0,
      11.0,
      -100.0
    ],
    [
      26.0,
      11.0,
      -100.0
    ],
    [
      24.0,
      11.0,
      -100.0
    ],
    [
      22.0,
      11.0,
      -100.0
    ],
    [
      20.0,
      11.0,
      -100.0
    ],
    [
      18.0,
      11.0,
      -100.0
    ],
    [
      16.0,
      11.0,
      -100.0
    ],
    [
      14.0,
      11.0,
      -100.0
    ],
    [
      12.0,
      11.0,
      -100.0
    ],
    [
      10.0,
      11.0,
      -100.0
    ],
    [
      8.0,
      11.0,
      -100.0
    ],
    [
      6.0,
      11.0,
      -100.0
    ],
    [
      4.0,
      11.0,
      -100.0
    ],
    [
      2.0,
      13.0,
      -100.0
    ],
    [
      4.0,
      13.0,
      -100.0
    ],
    [
      6.0,
      13.0,
      -100.0
    ],
    [
      8.0,
      13.0,
      -100.0
    ],
    [
      10.0,
      13.0,
      -100.0
    ],
    [
      12.0,
      13.0,
      -100.0
    ],
    [
      14.0,
      13.0,
      -100.0
    ],
    [
      16.0,
      13.0,
      -100.0
    ],
    [
      18.0,
      13.0,
      -100.0
    ],
    [
      20.0,
      13.0,
      -100.0
    ],
    [
      22.0,
      13.0,
      -100.0
    ],
    [
      24.0,
      13.0,
      -100.0
    ],
    [
      26.0,
      13.0,
      -100.0
    ],
    [
      28.0,
      13.0,
      -100.0
    ],
    [
      30.0,
      13.0,
      -100.0
    ],
    [
      32.0,
      13.0,
      -100.0
    ],
    [
      34.0,
      13.0,
      -100.0
    ],
    [
      36.0,
      13.0,
      -100.0
    ],
    [
      38.0,
      13.0,
      -100.0
    ],
    [
      40.0,
      13.0,
      -100.0
    ],
    [
      42.0,
      13.0,
      -100.0
    ],
    [
      44.0,
      13.0,
      -100.0
    ],
    [
      46.0,
      13.0,
      -100.0
    ],
    [
      48.0,
      13.0,
      -100.0
    ],
    [
      50.0,
      13.0,
      -100.0
    ],
    [
      52.0,
      13.0,
      -100.0
    ],
    [
      54.0,
      13.0,
      -100.0
    ],
    [
      56.0,
      13.0,
      -100.0
    ],
    [
      58.0,
      13.0,
      -100.0
    ],
    [
      60.0,
      13.0,
      -100.0
    ],
    [
      62.0,
      13.0,
      -100.0
    ],
    [
      64.0,
      13.0,
      -100.0
    ],
    [
      66.0,
      13.0,
      -100.0
    ],
    [
      68.0,
      13.0,
      -100.0
    ],
    [
      70.0,
      13.0,
      -100.0
    ],
    [
      72.0,
      13.0,
      -100.0
    ],
    [
      74.0,
      13.0,
      -100.0
    ],
    [
      76.0,
      13.0,
      -100.0
    ],
    [
      78.0,
      13.0,
      -100.0
    ],
    [
      80.0,
      13.0,
      -100.0
    ],
    [
      82.0,
      13.0,
      -100.0
    ],
    [
      84.0,
      13.0,
      -100.0
    ],
    [
      86.0,
      13.0,
      -100.0
    ],
    [
      88.0,
      13.0,
      -100.0
    ],
    [
      90.0,
      13.0,
      -100.0
    ],
    [
      92.0,
      13.0,
      -100.0
    ],
    [
      94.0,
      13.0,
      -100.0
    ],
    [
      96.0,
      13.0,
      -100.0
    ],
    [
      98.0,
      13.0,
      -100.0
    ],
    [
      100.0,
      13.0,
      -100.0
    ],
    [
      102.0,
      13.0,
      -100.0
    ],
    [
      104.0,
      13.0,
      -100.0
    ],
    [
      106.0,
      13.0,
      -100.0
    ],
    [
      108.0,
      13.0,
      -100.0
    ],
    [
      110.0,
      13.0,
      -100.0
    ],
    [
      112.0,
      13.0,
      -100.0
    ],
    [
      114.0,
      13.0,
      -100.0
    ],
    [
      116.0,
      13.0,
      -100.0
    ],
    [
      118.0,
      13.0,
      -100.0
    ],
    [
      120.0,
      13.0,
      -100.0
    ],
    [
      122.0,
      13.0,
      -100.0
    ],
    [
      124.0,
      13.0,
      -100.0
    ],
    [
      126.0,
      13.0,
      -100.0
    ],
    [
      128.0,
      13.0,
      -100.0
    ],
    [
      130.0,
      13.0,
      -100.0
    ],
    [
      132.0,
      13.0,
      -100.0
    ],
    [
      134.0,
      13.0,
      -100.0
    ],
    [
      136.0,
      15.0,
      -100.0
    ],
    [
      134.0,
      15.0,
      -100.0
    ],
    [
      132.0,
      15.0,
      -100.0
    ],
    [
      130.0,
      15.0,
      -100.0
    ],
    [
      128.0,
      15.0,
      -100.0
    ],
    [
      126.0,
      15.0,
      -100.0
    ],
    [
      124.0,
      15.0,
      -100.0
    ],
    [
      122.0,
      15.0,
      -100.0
    ],
    [
      120.0,
      15.0,
      -100.0
    ],
    [
      118.0,
      15.0,
      -100.0
    ],
    [
      116.0,
      15.0,
      -100.0
    ],
    [
      114.0,
      15.0,
      -100.0
    ],
    [
      112.0,
      15.0,
      -100.0
    ],
    [
      110.0,
      15.0,
      -100.0
    ],
    [
      108.0,
      15.0,
      -100.0
    ],
    [
      106.0,
      15.0,
      -100.0
    ],
    [
      104.0,
      15.0,
      -100.0
    ],
    [
      102.0,
      15.0,
      -100.0
    ],
    [
      100.0,
      15.0,
      -100.0
    ],
    [
      98.0,
      15.0,
      -100.0
    ],
    [
      96.0,
      15.0,
      -100.0
    ],
    [
      94.0,
      15.0,
      -100.0
    ],
    [
      92.0,
      15.0,
      -100.0
    ],
    [
      90.0,
      15.0,
      -100.0
    ],
    [
      88.0,
      15.0,
      -100.0
    ],
    [
      86.0,
      15.0,
      -100.0
    ],
    [
      84.0,
      15.0,
      -100.0
    ],
    [
      82.0,
      15.0,
      -100.0
    ],
    [
      80.0,
      15.0,
      -100.0
    ],
    [
      78.0,
      15.0,
      -100.0
    ],
    [
      76.0,
      15.0,
      -100.0
    ],
    [
      74.0,
      15.0,
      -100.0
    ],
    [
      72.0,
      15.0,
      -100.0
    ],
    [
      70.0,
      15.0,
      -100.0
    ],
    [
      68.0,
      15.0,
      -100.0
    ],
    [
      66.0,
      15.0,
      -100.0
    ],
    [
      64.0,
      15.0,
      -100.0
    ],
    [
      62.0,
      15.0,
      -100.0
    ],
    [
      60.0,
      15.0,
      -100.0
    ],
    [
      58.0,
      15.0,
      -100.0
    ],
    [
      56.0,
      15.0,
      -100.0
    ],
    [
      54.0,
      15.0,
      -100.0
    ],
    [
      52.0,
      15.0,
      -100.0
    ],
    [
      50.0,
      15.0,
      -100.0
    ],
    [
      48.0,
      15.0,
      -100.0
    ],
    [
      46.0,
      15.0,
      -100.0
    ],
    [
      44.0,
      15.0,
      -100.0
    ],
    [
      42.0,
      15.0,
      -100.0
    ],
    [
      40.0,
      15.0,
      -100.0
    ],
    [
      38.0,
      15.0,
      -100.0
    ],
    [
      36.0,
      15.0,
      -100.0
    ],
    [
      34.0,
      15.0,
      -100.0
    ],
    [
      32.0,
      15.0,
      -100.0
    ],
    [
      30.0,
      15.0,
      -100.0
    ],
    [
      28.0,
      15.0,
      -100.0
    ],
    [
      26.0,
      15.0,
      -100.0
    ],
    [
      24.0,
      15.0,
      -100.0
    ],
    [
      22.0,
      15.0,
      -100.0
    ],
    [
      20.0,
      15.0,
      -100.0
    ],
    [
      18.0,
      15.0,
      -100.0
    ],
    [
      16.0,
      15.0,
      -100.0
    ],
    [
      14.0,
      15.0,
      -100.0
    ],
    [
      12.0,
      15.0,
      -100.0
    ],
    [
      10.0,
      15.0,
      -100.0
    ],
    [
      8.0,
      15.0,
      -100.0
    ],
    [
      6.0,
      15.0,
      -100.0
    ],
    [
      4.0,
      15.0,
      -100.0
    ],
    [
      2.0,
      17.0,
      -100.0
    ],
    [
      4.0,
      17.0,
      -100.0
    ],
    [
      6.0,
      17.0,
      -100.0
    ],
    [
      8.0,
      17.0,
      -100.0
    ],
    [
      10.0,
      17.0,
      -100.0
    ],
    [
      12.0,
      17.0,
      -100.0
    ],
    [
      14.0,
      17.0,
      -100.0
    ],
    [
      16.0,
      17.0,
      -100.0
    ],
    [
      18.0,
      17.0,
      -100.0
    ],
    [
      20.0,
      17.0,
      -100.0
    ],
    [
      22.0,
      17.0,
      -100.0
    ],
    [
      24.0,
      17.0,
      -100.0
    ],
    [
      26.0,
      17.0,
      -100.0
    ],
    [
      28.0,
      17.0,
      -100.0
    ],
    [
      30.0,
      17.0,
      -100.0
    ],
    [
      32.0,
      17.0,
      -100.0
    ],
    [
      34.0,
      17.0,
      -100.0
    ],
    [
      36.0,
      17.0,
      -100.0
    ],
    [
      38.0,
      17.0,
      -100.0
    ],
    [
      40.0,
      17.0,
      -100.0
    ],
    [
      42.0,
      17.0,
      -100.0
    ],
    [
      44.0,
      17.0,
      -100.0
    ],
    [
      46.0,
      17.0,
      -100.0
    ],
    [
      48.0,
      17.0,
      -100.0
    ],
    [
      50.0,
      17.0,
      -100.0
    ],
    [
      52.0,
      17.0,
      -100.0
    ],
    [
      54.0,
      17.0,
      -100.0
    ],
    [
      56.0,
      17.0,
      -100.0
    ],
    [
      58.0,
      17.0,
      -100.0
    ],
    [
      60.0,
      17.0,
      -100.0
    ],
    [
      62.0,
      17.0,
      -100.0
    ],
    [
      64.0,
      17.0,
      -100.0
    ],
    [
      66.0,
      17.0,
      -100.0
    ],
    [
      68.0,
      17.0,
      -100.0
    ],
    [
      70.0,
      17.0,
      -100.0
    ],
    [
      72.0,
      17.0,
      -100.0
    ],
    [
      74.0,
      17.0,
      -100.0
    ],
    [
      76.0,
      17.0,
      -100.0
    ],
    [
      78.0,
      17.0,
      -100.0
    ],
    [
      80.0,
      17.0,
      -100.0
    ],
    [
      82.0,
      17.0,
      -100.0
    ],
    [
      84.0,
      17.0,
      -100.0
    ],
    [
      86.0,
      17.0,
      -100.0
    ],
    [
      88.0,
      17.0,
      -100.0
    ],
    [
      90.0,
      17.0,
      -100.0
    ],
    [
      92.0,
      17.0,
      -100.0
    ],
    [
      94.0,
      17.0,
      -100.0
    ],
    [
      96.0,
      17.0,
      -100.0
    ],
    [
      98.0,
      17.0,
      -100.0
    ],
    [
      100.0,
      17.0,
      -100.0
    ],
    [
      102.0,
      17.0,
      -100.0
    ],
    [
      104.0,
      17.0,
      -100.0
    ],
    [
      106.0,
      17.0,
      -100.0
    ],
    [
      108.0,
      17.0,
      -100.0
    ],
    [
      110.0,
      17.0,
      -100.0
    ],
    [
      112.0,
      17.0,
      -100.0
    ],
    [
      114.0,
      17.0,
      -100.0
    ],
    [
      116.0,
      17.0,
      -100.0
    ],
    [
      118.0,
      17.0,
      -100.0
    ],
    [
      120.0,
      17.0,
      -100.0
    ],
    [
      122.0,
      17.0,
      -100.0
    ],
    [
      124.0,
      17.0,
      -100.0
    ],
    [
      126.0,
      17.0,
      -100.0
    ],
    [
      128.0,
      17.0,
      -100.0
    ],
    [
      130.0,
      17.0,
      -100.0
    ],
    [
      132.0,
      17.0,
      -100.0
    ],
    [
      134.0,
      17.0,
      -100.0
    ],
    [
      1.3116919604550765,
      1.6882418063916151,
      -100.0
    ],
    [
      1.0859617294586377,
      1.490641546234159,
      -100.0
    ],
    [
      0.8602314984621989,
      1.2930412860767024,
      -100.0
    ],
    [
      0.6345012674657602,
      1.0954410259192462,
      -100.0
    ],
    [
      0.40877103646932145,
      0.89784076576179,
      -100.0
    ],
    [
      0.1830408054728827,
      0.7002405056043337,
      -100.0
    ],
    [
      -0.04268942552355606,
      0.5026402454468775,
      -100.0
    ],
    [
      -0.26841965651999483,
      0.30503998528942117,
      -100.0
    ],
    [
      -0.4941498875164336,
      0.1074397251319649,
      -100.0
    ],
    [
      -0.7198801185128724,
      -0.0901605350254914,
      -100.0
    ],
    [
      -0.9456103495093111,
      -0.28776079518294767,
      -100.0
    ],
    [
      -1.17134058050575,
      -0.48536105534040397,
      -100.0
    ],
    [
      -1.3970708115021888,
      -0.6829613154978602,
      -100.0
    ],
    [
      -1.6228010424986277,
      -0.8805615756553165,
      -100.0
    ],
    [
      -1.8485312734950665,
      -1.0781618358127727,
      -100.0
    ],
    [
      -2.0742615044915054,
      -1.275762095970229,
      -100.0
    ],
    [
      -2.2999917354879442,
      -1.4733623561276852,
      -100.0
    ],
    [
      -2.525721966484383,
      -1.6709626162851414,
      -100.0
    ],
    [
      -2.751452197480822,
      -1.8685628764425977,
      -100.0
    ],
    [
      -2.977182428477261,
      -2.066163136600054,
      -100.0
    ],
    [
      -3.2029126594736996,
      -2.2637633967575104,
      -100.0
    ],
    [
      -3.4286428904701385,
      -2.461363656914967,
      -100.0
    ],
    [
      -3.6543731214665773,
      -2.6589639170724233,
      -100.0
    ],
    [
      -3.880103352463016,
      -2.8565641772298798,
      -100.0
    ],
    [
      -4.105833583459455,
      -3.0541644373873362,
      -100.0
    ],
    [
      -4.331563814455893,
      -3.2517646975447927,
      -100.0
    ],
    [
      -4.557294045452331,
      -3.449364957702249,
      -100.0
    ],
    [
      -4.78302427644877,
      -3.6469652178597056,
      -100.0
    ],
    [
      -5.008754507445208,
      -3.844565478017162,
      -100.0
    ],
    [
      -5.234484738441647,
      -4.042165738174618,
      -100.0
    ],
    [
      -5.460214969438085,
      -4.239765998332074,
      -100.0
    ],
    [
      -5.6859452004345234,
      -4.43736625848953,
      -100.0
    ],
    [
      -5.911675431430962,
      -4.634966518646986,
      -100.0
    ],
    [
      -6.1374056624274,
      -4.832566778804442,
      -100.0
    ],
    [
      -6.363135893423839,
      -5.030167038961898,
      -100.0
    ],
    [
      -6.588866124420277,
      -5.227767299119354,
      -100.0
    ],
    [
      -6.8145963554167155,
      -5.42536755927681,
      -100.0
    ],
    [
      -7.040326586413154,
      -5.622967819434266,
      -100.0
    ],
    [
      -7.266056817409592,
      -5.820568079591722,
      -100.0
    ],
    [
      -7.491787048406031,
      -6.018168339749178,
      -100.0
    ],
    [
      -7.717517279402469,
      -6.215768599906634,
      -100.0
    ],
    [
      -7.9432475103989075,
      -6.41336886006409,
      -100.0
    ],
    [
      -8.168977741395347,
      -6.610969120221546,
      -100.0
    ],
    [
      -8.394707972391785,
      -6.808569380379002,
      -100.0
    ],
    [
      -8.620438203388224,
      -7.006169640536458,
      -100.0
    ],
    [
      -8.846168434384662,
      -7.203769900693914,
      -100.0
    ],
    [
      -9.0718986653811,
      -7.4013701608513704,
      -100.0
    ],
    [
      -9.297628896377539,
      -7.5989704210088265,
      -100.0
    ],
    [
      -9.523359127373977,
      -7.7965706811662825,
      -100.0
    ],
    [
      -9.749089358370416,
      -7.9941709413237385,
      -100.0
    ],
    [
      -9.974819589366854,
      -8.191771201481195,
      -100.0
    ],
    [
      -10.200549820363292,
      -8.389371461638651,
      -100.0
    ],
    [
      -10.426280051359731,
      -8.586971721796107,
      -100.0
    ],
    [
      -10.65201028235617,
      -8.784571981953563,
      -100.0
    ],
    [
      -10.877740513352608,
      -8.98217224211102,
      -100.0
    ],
    [
      -11.103470744349046,
      -9.179772502268476,
      -100.0
    ],
    [
      -11.329200975345485,
      -9.377372762425932,
      -100.0
    ],
    [
      -11.554931206341923,
      -9.574973022583388,
      -100.0
    ],
    [
      -11.780661437338361,
      -9.772573282740844,
      -100.0
    ],
    [
      -12.0063916683348,
      -9.9701735428983,
      -100.0
    ],
    [
      -12.232121899331238,
      -10.167773803055756,
      -100.0
    ],
    [
      -12.457852130327677,
      -10.365374063213212,
      -100.0
    ],
    [
      -12.683582361324115,
      -10.562974323370668,
      -100.0
    ],
    [
      -12.909312592320553,
      -10.760574583528124,
      -100.0
    ],
    [
      -13.135042823316992,
      -10.95817484368558,
      -100.0
    ],
    [
      -13.36077305431343,
      -11.155775103843036,
      -100.0
    ],
    [
      -13.586503285309869,
      -11.353375364000492,
      -100.0
    ],
    [
      -13.812233516306307,
      -11.550975624157948,
      -100.0
    ],
    [
      -14.037963747302745,
      -11.748575884315404,
      -100.0
    ],
    [
      -14.263693978299184,
      -11.94617614447286,
      -100.0
    ],
    [
      -14.489424209295622,
      -12.143776404630316,
      -100.0
    ],
    [
      -14.71515444029206,
      -12.341376664787772,
      -100.0
    ],
    [
      -14.940884671288499,
      -12.538976924945228,
      -100.0
    ],
    [
      -15.166614902284937,
      -12.736577185102684,
      -100.0
    ],
    [
      -15.392345133281376,
      -12.93417744526014,
      -100.0
    ],
    [
      -15.618075364277814,
      -13.131777705417596,
      -100.0
    ],
    [
      -15.843805595274253,
      -13.329377965575052,
      -100.0
    ],
    [
      -16.06953582627069,
      -13.526978225732508,
      -100.0
    ],
    [
      -16.29526605726713,
      -13.724578485889964,
      -100.0
    ],
    [
      -16.52099628826357,
      -13.92217874604742,
      -100.0
    ],
    [
      -16.74672651926001,
      -14.119779006204876,
      -100.0
    ],
    [
      -16.972456750256452,
      -14.317379266362332,
      -100.0
    ],
    [
      -17.198186981252892,
      -14.514979526519788,
      -100.0
    ],
    [
      -17.423917212249332,
      -14.712579786677244,
      -100.0
    ],
    [
      -17.649647443245772,
      -14.9101800468347,
      -100.0
    ],
    [
      -17.875377674242213,
      -15.107780306992156,
      -100.0
    ],
    [
      -18.101107905238653,
      -15.305380567149612,
      -100.0
    ],
    [
      -18.326838136235093,
      -15.502980827307068,
      -100.0
    ],
    [
      -18.552568367231533,
      -15.700581087464524,
      -100.0
    ],
    [
      -18.778298598227973,
      -15.89818134762198,
      -100.0
    ],
    [
      -19.004028829224413,
      -16.095781607779436,
      -100.0
    ],
    [
      -19.229759060220854,
      -16.293381867936894,
      -100.0
    ],
    [
      -19.455489291217294,
      -16.490982128094352,
      -100.0
    ],
    [
      -19.681219522213734,
      -16.68858238825181,
      -100.0
    ],
    [
      -19.906949753210174,
      -16.886182648409267,
      -100.0
    ],
    [
      -20.132679984206614,
      -17.083782908566725,
      -100.0
    ],
    [
      -20.358410215203055,
      -17.281383168724183,
      -100.0
    ],
    [
      -20.584140446199495,
      -17.47898342888164,
      -100.0
    ],
    [
      -20.809870677195935,
      -17.6765836890391,
      -100.0
    ],
    [
      -21.035600908192375,
      -17.874183949196556,
      -100.0
    ],
    [
      -21.261331139188815,
      -18.071784209354014,
      -100.0
    ],
    [
      -21.487061370185256,
      -18.269384469511472,
      -100.0
    ],
    [
      -21.712791601181696,
      -18.46698472966893,
      -100.0
    ],
    [
      -21.938521832178136,
      -18.664584989826388,
      -100.0
    ],
    [
      -22.164252063174576,
      -18.862185249983845,
      -100.0
    ],
    [
      -22.389982294171016,
      -19.059785510141303,
      -100.0
    ],
    [
      -22.615712525167456,
      -19.25738577029876,
      -100.0
    ],
    [
      -22.841442756163897,
      -19.45498603045622,
      -100.0
    ],
    [
      -23.067172987160337,
      -19.652586290613677,
      -100.0
    ],
    [
      -23.292903218156777,
      -19.850186550771134,
      -100.0
    ],
    [
      -23.518633449153217,
      -20.047786810928592,
      -100.0
    ],
    [
      -23.744363680149657,
      -20.24538707108605,
      -100.0
    ],
    [
      -23.970093911146098,
      -20.442987331243508,
      -100.0
    ],
    [
      -24.195824142142538,
      -20.640587591400966,
      -100.0
    ],
    [
      -24.421554373138978,
      -20.838187851558423,
      -100.0
    ],
    [
      -24.647284604135418,
      -21.03578811171588,
      -100.0
    ],
    [
      -24.87301483513186,
      -21.23338837187334,
      -100.0
    ],
    [
      -25.0987450661283,
      -21.430988632030797,
      -100.0
    ],
    [
      -25.32447529712474,
      -21.628588892188255,
      -100.0
    ],
    [
      -25.55020552812118,
      -21.826189152345712,
      -100.0
    ],
    [
      -25.77593575911762,
      -22.02378941250317,
      -100.0
    ],
    [
      -26.00166599011406,
      -22.221389672660628,
      -100.0
    ],
    [
      -26.2273962211105,
      -22.418989932818086,
      -100.0
    ],
    [
      -26.45312645210694,
      -22.616590192975544,
      -100.0
    ],
    [
      -26.67885668310338,
      -22.814190453133,
      -100.0
    ],
    [
      -26.90458691409982,
      -23.01179071329046,
      -100.0
    ],
    [
      -27.13031714509626,
      -23.209390973447917,
      -100.0
    ],
    [
      -27.3560473760927,
      -23.406991233605375,
      -100.0
    ],
    [
      -27.58177760708914,
      -23.604591493762832,
      -100.0
    ],
    [
      -27.80750783808558,
      -23.80219175392029,
      -100.0
    ],
    [
      -28.03323806908202,
      -23.999792014077748,
      -100.0
    ],
    [
      -28.25896830007846,
      -24.197392274235206,
      -100.0
    ],
    [
      -28.4846985310749,
      -24.394992534392664,
      -100.0
    ],
    [
      -28.71042876207134,
      -24.59259279455012,
      -100.0
    ],
    [
      -28.93615899306778,
      -24.79019305470758,
      -100.0
    ],
    [
      -29.161889224064222,
      -24.987793314865037,
      -100.0
    ],
    [
      -29.387619455060662,
      -25.185393575022495,
      -100.0
    ],
    [
      -29.613349686057102,
      -25.382993835179953,
      -100.0
    ],
    [
      -29.839079917053542,
      -25.58059409533741,
      -100.0
    ],
    [
      -30.064810148049983,
      -25.77819435549487,
      -100.0
    ],
    [
      -30.290540379046423,
      -25.975794615652326,
      -100.0
    ],
    [
      -30.516270610042863,
      -26.173394875809784,
      -100.0
    ],
    [
      -30.742000841039303,
      -26.37099513596724,
      -100.0
    ],
    [
      -30.967731072035743,
      -26.5685953961247,
      -100.0
    ],
    [
      -31.193461303032183,
      -26.766195656282157,
      -100.0
    ],
    [
      -31.419191534028624,
      -26.963795916439615,
      -100.0
    ],
    [
      -31.644921765025064,
      -27.161396176597073,
      -100.0
    ],
    [
      -31.870651996021504,
      -27.35899643675453,
      -100.0
    ],
    [
      -32.09638222701794,
      -27.55659669691199,
      -100.0
    ],
    [
      -32.32211245801438,
      -27.754196957069446,
      -100.0
    ],
    [
      -32.54784268901082,
      -27.951797217226904,
      -100.0
    ],
    [
      -32.77357292000726,
      -28.149397477384362,
      -100.0
    ],
    [
      -32.9993031510037,
      -28.34699773754182,
      -100.0
    ],
    [
      -33.22503338200014,
      -28.544597997699277,
      -100.0
    ],
    [
      -33.45076361299658,
      -28.742198257856735,
      -100.0
    ],
    [
      -33.67649384399302,
      -28.939798518014193,
      -100.0
    ],
    [
      -33.90222407498946,
      -29.13739877817165,
      -100.0
    ],
    [
      -34.1279543059859,
      -29.33499903832911,
      -100.0
    ],
    [
      -34.35368453698234,
      -29.532599298486566,
      -100.0
    ],
    [
      -34.57941476797878,
      -29.730199558644024,
      -100.0
    ],
    [
      -34.80514499897522,
      -29.927799818801482,
      -100.0
    ],
    [
      -35.03087522997166,
      -30.12540007895894,
      -100.0
    ],
    [
      -35.2566054609681,
      -30.323000339116398,
      -100.0
    ],
    [
      -35.48233569196454,
      -30.520600599273855,
      -100.0
    ],
    [
      -35.708065922960984,
      -30.718200859431313,
      -100.0
    ],
    [
      -35.933796153957424,
      -30.91580111958877,
      -100.0
    ],
    [
      -36.159526384953864,
      -31.11340137974623,
      -100.0
    ],
    [
      -36.385256615950304,
      -31.311001639903687,
      -100.0
    ],
    [
      -36.610986846946744,
      -31.508601900061144,
      -100.0
    ],
    [
      -36.836717077943185,
      -31.706202160218602,
      -100.0
    ],
    [
      -37.062447308939625,
      -31.90380242037606,
      -100.0
    ],
    [
      -37.288177539936065,
      -32.10140268053352,
      -100.0
    ],
    [
      -37.513907770932505,
      -32.299002940690976,
      -100.0
    ],
    [
      -37.739638001928945,
      -32.49660320084843,
      -100.0
    ],
    [
      -37.965368232925385,
      -32.69420346100589,
      -100.0
    ],
    [
      -38.191098463921826,
      -32.89180372116335,
      -100.0
    ],
    [
      -38.416828694918266,
      -33.08940398132081,
      -100.0
    ],
    [
      -38.642558925914706,
      -33.287004241478265,
      -100.0
    ],
    [
      -38.868289156911146,
      -33.48460450163572,
      -100.0
    ],
    [
      -39.094019387907586,
      -33.68220476179318,
      -100.0
    ],
    [
      -39.31974961890403,
      -33.87980502195064,
      -100.0
    ],
    [
      -39.54547984990047,
      -34.077405282108096,
      -100.0
    ],
    [
      -39.77121008089691,
      -34.27500554226555,
      -100.0
    ],
    [
      -39.99694031189335,
      -34.47260580242301,
      -100.0
    ],
    [
      -40.22267054288979,
      -34.67020606258047,
      -100.0
    ],
    [
      -40.44840077388623,
      -34.86780632273793,
      -100.0
    ],
    [
      -40.67413100488267,
      -35.065406582895385,
      -100.0
    ],
    [
      -40.89986123587911,
      -35.26300684305284,
      -100.0
    ],
    [
      -41.12559146687555,
      -35.4606071032103,
      -100.0
    ],
    [
      -41.35132169787199,
      -35.65820736336776,
      -100.0
    ],
    [
      -41.57705192886843,
      -35.855807623525216,
      -100.0
    ],
    [
      -41.80278215986487,
      -36.053407883682674,
      -100.0
    ],
    [
      -42.02851239086131,
      -36.25100814384013,
      -100.0
    ],
    [
      -42.25424262185775,
      -36.44860840399759,
      -100.0
    ],
    [
      -42.47997285285419,
      -36.64620866415505,
      -100.0
    ],
    [
      -42.70570308385063,
      -36.843808924312505,
      -100.0
    ],
    [
      -42.93143331484707,
      -37.04140918446996,
      -100.0
    ],
    [
      -43.15716354584351,
      -37.23900944462742,
      -100.0
    ],
    [
      -43.38289377683995,
      -37.43660970478488,
      -100.0
    ],
    [
      -43.60862400783639,
      -37.634209964942336,
      -100.0
    ],
    [
      -43.83435423883283,
      -37.831810225099794,
      -100.0
    ],
    [
      -44.06008446982927,
      -38.02941048525725,
      -100.0
    ],
    [
      -44.28581470082571,
      -38.22701074541471,
      -100.0
    ],
    [
      -44.51154493182215,
      -38.42461100557217,
      -100.0
    ],
    [
      -44.73727516281859,
      -38.622211265729625,
      -100.0
    ],
    [
      -44.96300539381503,
      -38.81981152588708,
      -100.0
    ],
    [
      -45.18873562481147,
      -39.01741178604454,
      -100.0
    ],
    [
      -45.41446585580791,
      -39.215012046202,
      -100.0
    ],
    [
      -45.64019608680435,
      -39.412612306359456,
      -100.0
    ],
    [
      -45.86592631780079,
      -39.610212566516914,
      -100.0
    ],
    [
      -46.09165654879723,
      -39.80781282667437,
      -100.0
    ],
    [
      -46.31738677979367,
      -40.00541308683183,
      -100.0
    ],
    [
      -46.54311701079011,
      -40.20301334698929,
      -100.0
    ],
    [
      -46.76884724178655,
      -40.400613607146745,
      -100.0
    ],
    [
      -46.99457747278299,
      -40.5982138673042,
      -100.0
    ],
    [
      -47.22030770377943,
      -40.79581412746166,
      -100.0
    ],
    [
      -47.44603793477587,
      -40.99341438761912,
      -100.0
    ],
    [
      -47.67176816577231,
      -41.191014647776576,
      -100.0
    ],
    [
      -47.89749839676875,
      -41.388614907934034,
      -100.0
    ],
    [
      -48.123228627765194,
      -41.58621516809149,
      -100.0
    ],
    [
      -48.348958858761634,
      -41.78381542824895,
      -100.0
    ],
    [
      -48.574689089758074,
      -41.98141568840641,
      -100.0
    ],
    [
      -48.800419320754514,
      -42.179015948563865,
      -100.0
    ],
    [
      -49.026149551750954,
      -42.37661620872132,
      -100.0
    ],
    [
      -49.251879782747395,
      -42.57421646887878,
      -100.0
    ],
    [
      -49.477610013743835,
      -42.77181672903624,
      -100.0
    ],
    [
      -49.703340244740275,
      -42.9694169891937,
      -100.0
    ],
    [
      -49.929070475736715,
      -43.167017249351154,
      -100.0
    ],
    [
      -50.154800706733155,
      -43.36461750950861,
      -100.0
    ],
    [
      -50.380530937729596,
      -43.56221776966607,
      -100.0
    ],
    [
      -50.606261168726036,
      -43.75981802982353,
      -100.0
    ],
    [
      -50.831991399722476,
      -43.957418289980986,
      -100.0
    ],
    [
      -51.057721630718916,
      -44.15501855013844,
      -100.0
    ],
    [
      -51.283451861715356,
      -44.3526188102959,
      -100.0
    ],
    [
      -51.5091820927118,
      -44.55021907045336,
      -100.0
    ],
    [
      -51.73491232370824,
      -44.74781933061082,
      -100.0
    ],
    [
      -51.96064255470468,
      -44.945419590768275,
      -100.0
    ],
    [
      -52.18637278570112,
      -45.14301985092573,
      -100.0
    ],
    [
      -52.41210301669756,
      -45.34062011108319,
      -100.0
    ],
    [
      -52.637833247694,
      -45.53822037124065,
      -100.0
    ],
    [
      -52.86356347869044,
      -45.735820631398106,
      -100.0
    ],
    [
      -53.08929370968688,
      -45.93342089155556,
      -100.0
    ],
    [
      -53.31502394068332,
      -46.13102115171302,
      -100.0
    ],
    [
      -53.54075417167976,
      -46.32862141187048,
      -100.0
    ],
    [
      -53.7664844026762,
      -46.52622167202794,
      -100.0
    ],
    [
      -53.99221463367264,
      -46.723821932185395,
      -100.0
    ],
    [
      -54.21794486466908,
      -46.92142219234285,
      -100.0
    ],
    [
      -54.44367509566552,
      -47.11902245250031,
      -100.0
    ],
    [
      -54.66940532666196,
      -47.31662271265777,
      -100.0
    ],
    [
      -54.8951355576584,
      -47.514222972815226,
      -100.0
    ],
    [
      -55.12086578865484,
      -47.711823232972684,
      -100.0
    ],
    [
      -55.34659601965128,
      -47.90942349313014,
      -100.0
    ],
    [
      -55.57232625064772,
      -48.1070237532876,
      -100.0
    ],
    [
      -55.79805648164416,
      -48.30462401344506,
      -100.0
    ],
    [
      -56.0237867126406,
      -48.502224273602515,
      -100.0
    ],
    [
      -56.24951694363704,
      -48.69982453375997,
      -100.0
    ],
    [
      -56.47524717463348,
      -48.89742479391743,
      -100.0
    ],
    [
      -56.70097740562992,
      -49.09502505407489,
      -100.0
    ],
    [
      -56.92670763662636,
      -49.292625314232346,
      -100.0
    ],
    [
      -57.1524378676228,
      -49.490225574389804,
      -100.0
    ],
    [
      -57.37816809861924,
      -49.68782583454726,
      -100.0
    ],
    [
      -57.60389832961568,
      -49.88542609470472,
      -100.0
    ],
    [
      -57.82962856061212,
      -50.08302635486218,
      -100.0
    ],
    [
      -58.05535879160856,
      -50.280626615019635,
      -100.0
    ],
    [
      -58.281089022605,
      -50.47822687517709,
      -100.0
    ],
    [
      -58.50681925360144,
      -50.67582713533455,
      -100.0
    ],
    [
      -58.73254948459788,
      -50.87342739549201,
      -100.0
    ],
    [
      -58.95827971559432,
      -51.071027655649466,
      -100.0
    ],
    [
      -59.18400994659076,
      -51.268627915806924,
      -100.0
    ],
    [
      -59.4097401775872,
      -51.46622817596438,
      -100.0
    ],
    [
      -59.63547040858364,
      -51.66382843612184,
      -100.0
    ],
    [
      -59.86120063958008,
      -51.8614286962793,
      -100.0
    ],
    [
      -60.08693087057652,
      -52.059028956436755,
      -100.0
    ],
    [
      -60.312661101572964,
      -52.25662921659421,
      -100.0
    ],
    [
      -60.538391332569404,
      -52.45422947675167,
      -100.0
    ],
    [
      -60.764121563565844,
      -52.65182973690913,
      -100.0
    ],
    [
      -60.989851794562284,
      -52.849429997066586,
      -100.0
    ],
    [
      -61.215582025558724,
      -53.047030257224044,
      -100.0
    ],
    [
      -61.441312256555165,
      -53.2446305173815,
      -100.0
    ],
    [
      -61.667042487551605,
      -53.44223077753896,
      -100.0
    ],
    [
      -61.892772718548045,
      -53.63983103769642,
      -100.0
    ],
    [
      -62.118502949544485,
      -53.837431297853875,
      -100.0
    ],
    [
      -62.344233180540925,
      -54.03503155801133,
      -100.0
    ],
    [
      -62.569963411537366,
      -54.23263181816879,
      -100.0
    ],
    [
      -62.795693642533806,
      -54.43023207832625,
      -100.0
    ],
    [
      -63.021423873530246,
      -54.62783233848371,
      -100.0
    ],
    [
      -63.247154104526686,
      -54.825432598641164,
      -100.0
    ],
    [
      -63.472884335523126,
      -55.02303285879862,
      -100.0
    ],
    [
      -63.698614566519566,
      -55.22063311895608,
      -100.0
    ],
    [
      -63.92434479751601,
      -55.41823337911354,
      -100.0
    ],
    [
      -64.15007502851245,
      -55.615833639270996,
      -100.0
    ],
    [
      -64.37580525950888,
      -55.81343389942845,
      -100.0
    ],
    [
      -64.60153549050531,
      -56.01103415958591,
      -100.0
    ],
    [
      -64.82726572150175,
      -56.20863441974337,
      -100.0
    ],
    [
      -65.05299595249818,
      -56.40623467990083,
      -100.0
    ],
    [
      -65.27872618349461,
      -56.603834940058285,
      -100.0
    ],
    [
      -65.50445641449105,
      -56.80143520021574,
      -100.0
    ],
    [
      -65.73018664548748,
      -56.9990354603732,
      -100.0
    ],
    [
      -65.95591687648391,
      -57.19663572053066,
      -100.0
    ],
    [
      -66.18164710748034,
      -57.394235980688116,
      -100.0
    ],
    [
      -66.40737733847678,
      -57.59183624084557,
      -100.0
    ],
    [
      -66.63310756947321,
      -57.78943650100303,
      -100.0
    ],
    [
      -66.85883780046964,
      -57.98703676116049,
      -100.0
    ],
    [
      -67.08456803146608,
      -58.18463702131795,
      -100.0
    ],
    [
      -67.31029826246251,
      -58.382237281475405,
      -100.0
    ],
    [
      -67.53602849345894,
      -58.57983754163286,
      -100.0
    ],
    [
      -67.76175872445538,
      -58.77743780179032,
      -100.0
    ],
    [
      -67.98748895545181,
      -58.97503806194778,
      -100.0
    ],
    [
      -68.21321918644824,
      -59.172638322105236,
      -100.0
    ],
    [
      -68.43894941744468,
      -59.370238582262694,
      -100.0
    ],
    [
      -68.66467964844111,
      -59.56783884242015,
      -100.0
    ],
    [
      -68.89040987943754,
      -59.76543910257761,
      -100.0
    ],
    [
      -69.11614011043397,
      -59.96303936273507,
      -100.0
    ],
    [
      -69.34187034143041,
      -60.160639622892525,
      -100.0
    ],
    [
      -69.56760057242684,
      -60.35823988304998,
      -100.0
    ],
    [
      -69.79333080342327,
      -60.55584014320744,
      -100.0
    ],
    [
      -70.0190610344197,
      -60.7534404033649,
      -100.0
    ],
    [
      -70.24479126541614,
      -60.951040663522356,
      -100.0
    ],
    [
      -70.47052149641257,
      -61.148640923679814,
      -100.0
    ],
    [
      -70.696251727409,
      -61.34624118383727,
      -100.0
    ],
    [
      -70.92198195840544,
      -61.54384144399473,
      -100.0
    ],
    [
      -71.14771218940187,
      -61.74144170415219,
      -100.0
    ],
    [
      -71.3734424203983,
      -61.939041964309645,
      -100.0
    ],
    [
      -71.59917265139474,
      -62.1366422244671,
      -100.0
    ],
    [
      -71.82490288239117,
      -62.33424248462456,
      -100.0
    ],
    [
      -72.0506331133876,
      -62.53184274478202,
      -100.0
    ],
    [
      -72.27636334438404,
      -62.729443004939476,
      -100.0
    ],
    [
      -72.50209357538047,
      -62.927043265096934,
      -100.0
    ],
    [
      -72.7278238063769,
      -63.12464352525439,
      -100.0
    ],
    [
      -72.95355403737334,
      -63.32224378541185,
      -100.0
    ],
    [
      -73.17928426836977,
      -63.51984404556931,
      -100.0
    ],
    [
      -73.4050144993662,
      -63.717444305726765,
      -100.0
    ],
    [
      -73.63074473036264,
      -63.91504456588422,
      -100.0
    ],
    [
      -73.85647496135907,
      -64.11264482604167,
      -100.0
    ],
    [
      -74.0822051923555,
      -64.31024508619913,
      -100.0
    ],
    [
      -74.30793542335194,
      -64.50784534635659,
      -100.0
    ],
    [
      -74.53366565434837,
      -64.70544560651405,
      -100.0
    ],
    [
      -74.7593958853448,
      -64.9030458666715,
      -100.0
    ],
    [
      -74.98512611634123,
      -65.10064612682896,
      -100.0
    ],
    [
      -75.21085634733767,
      -65.29824638698642,
      -100.0
    ],
    [
      -75.4365865783341,
      -65.49584664714388,
      -100.0
    ],
    [
      -75.66231680933053,
      -65.69344690730134,
      -100.0
    ],
    [
      -75.88804704032697,
      -65.8910471674588,
      -100.0
    ],
    [
      -76.1137772713234,
      -66.08864742761625,
      -100.0
    ],
    [
      -76.33950750231983,
      -66.28624768777371,
      -100.0
    ],
    [
      -76.56523773331627,
      -66.48384794793117,
      -100.0
    ],
    [
      -76.7909679643127,
      -66.68144820808863,
      -100.0
    ],
    [
      -77.01669819530913,
      -66.87904846824608,
      -100.0
    ],
    [
      -77.24242842630557,
      -67.07664872840354,
      -100.0
    ],
    [
      -77.468158657302,
      -67.274248988561,
      -100.0
    ],
    [
      -77.69388888829843,
      -67.47184924871846,
      -100.0
    ],
    [
      -77.91961911929486,
      -67.66944950887591,
      -100.0
    ],
    [
      -78.1453493502913,
      -67.86704976903337,
      -100.0
    ],
    [
      -78.37107958128773,
      -68.06465002919083,
      -100.0
    ],
    [
      -78.59680981228416,
      -68.26225028934829,
      -100.0
    ],
    [
      -78.8225400432806,
      -68.45985054950575,
      -100.0
    ],
    [
      -79.04827027427703,
      -68.6574508096632,
      -100.0
    ],
    [
      -79.27400050527346,
      -68.85505106982066,
      -100.0
    ],
    [
      -79.4997307362699,
      -69.05265132997812,
      -100.0
    ],
    [
      -79.72546096726633,
      -69.25025159013558,
      -100.0
    ],
    [
      -79.95119119826276,
      -69.44785185029303,
      -100.0
    ],
    [
      -80.1769214292592,
      -69.64545211045049,
      -100.0
    ],
    [
      -80.40265166025563,
      -69.84305237060795,
      -100.0
    ],
    [
      -80.62838189125206,
      -70.04065263076541,
      -100.0
    ],
    [
      -80.8541121222485,
      -70.23825289092287,
      -100.0
    ],
    [
      -81.07984235324493,
      -70.43585315108032,
      -100.0
    ],
    [
      -81.30557258424136,
      -70.63345341123778,
      -100.0
    ],
    [
      -81.5313028152378,
      -70.83105367139524,
      -100.0
    ],
    [
      -81.75703304623423,
      -71.0286539315527,
      -100.0
    ],
    [
      -81.98276327723066,
      -71.22625419171015,
      -100.0
    ],
    [
      -82.2084935082271,
      -71.42385445186761,
      -100.0
    ],
    [
      -82.43422373922353,
      -71.62145471202507,
      -100.0
    ],
    [
      -82.65995397021996,
      -71.81905497218253,
      -100.0
    ],
    [
      -82.88568420121639,
      -72.01665523233999,
      -100.0
    ],
    [
      -83.11141443221283,
      -72.21425549249744,
      -100.0
    ],
    [
      -83.33714466320926,
      -72.4118557526549,
      -100.0
    ],
    [
      -83.56287489420569,
      -72.60945601281236,
      -100.0
    ],
    [
      -83.78860512520212,
      -72.80705627296982,
      -100.0
    ],
    [
      -84.01433535619856,
      -73.00465653312727,
      -100.0
    ],
    [
      -84.24006558719499,
      -73.20225679328473,
      -100.0
    ],
    [
      -84.46579581819142,
      -73.39985705344219,
      -100.0
    ],
    [
      -84.69152604918786,
      -73.59745731359965,
      -100.0
    ],
    [
      -84.91725628018429,
      -73.7950575737571,
      -100.0
    ],
    [
      -85.14298651118072,
      -73.99265783391456,
      -100.0
    ],
    [
      -85.36871674217716,
      -74.19025809407202,
      -100.0
    ],
    [
      -85.59444697317359,
      -74.38785835422948,
      -100.0
    ],
    [
      -85.82017720417002,
      -74.58545861438694,
      -100.0
    ],
    [
      -86.04590743516646,
      -74.7830588745444,
      -100.0
    ],
    [
      -86.27163766616289,
      -74.98065913470185,
      -100.0
    ],
    [
      -86.49736789715932,
      -75.17825939485931,
      -100.0
    ],
    [
      -86.72309812815575,
      -75.37585965501677,
      -100.0
    ],
    [
      -86.94882835915219,
      -75.57345991517423,
      -100.0
    ],
    [
      -87.17455859014862,
      -75.77106017533168,
      -100.0
    ],
    [
      -87.40028882114505,
      -75.96866043548914,
      -100.0
    ],
    [
      -87.62601905214149,
      -76.1662606956466,
      -100.0
    ],
    [
      -87.85174928313792,
      -76.36386095580406,
      -100.0
    ],
    [
      -88.07747951413435,
      -76.56146121596151,
      -100.0
    ]
  ]
}